{"url": "https://nightlies.apache.org/flink/flink-docs-stable/docs/dev/datastream/operators/process_function", "title": "Process Function #", "summary": "**Process Function**\n#  Process Function #\n##  The ProcessFunction #\nThe `ProcessFunction` is a low-level stream processing operation, giving access to the basic building blocks of all (acyclic) streaming applications:\n  * events (stream el…", "type": "docs-page", "subproject": "flink-core", "version": "stable", "lang": "en", "tags": ["checkpoint", "datastream", "datastream-api", "dev", "flink", "operators", "process_function", "savepoint", "sql", "state", "statefun", "watermark", "window"], "code_langs": [], "last_modified": "2026-07-07", "path_depth": 2}