{"url": "https://nightlies.apache.org/flink/flink-docs-release-1.17/docs/dev/table/concepts/time_attributes", "title": "Time Attributes #", "summary": "**Time Attributes**\n> This documentation is for an out-of-date version of Apache Flink. We recommend you use the latest stable version.\n#  Time Attributes #\nFlink can process data based on different notions of time.\n  * _Processing time_ re…", "type": "docs-page", "subproject": "flink-core", "version": "main", "lang": "en", "tags": ["concepts", "datastream-api", "dev", "flink", "flink-docs-release-1.17", "sql", "table", "time_attributes", "watermark", "window"], "code_langs": [], "last_modified": "2026-07-07", "path_depth": 2}