{"url": "http://nightlies.apache.org/flink/flink-docs-release-2.2/docs/dev/table/sourcessinks", "title": "User-defined Sources & Sinks #", "summary": "**User-defined Sources & Sinks**\n> This documentation is for an out-of-date version of Apache Flink. We recommend you use the latest stable version.\n#  User-defined Sources & Sinks #\n_Dynamic tables_ are the core concept of Flink’s Table &…", "type": "docs-page", "subproject": "flink-core", "version": "main", "lang": "en", "tags": ["cdc", "datastream-api", "dev", "flink", "flink-docs-release-2.2", "sourcessinks", "sql", "state", "table", "table-api", "watermark"], "code_langs": [], "last_modified": "2026-07-07", "path_depth": 2}