{"url": "https://nightlies.apache.org/flink/flink-docs-master/zh/docs/deployment/trace_reporters", "title": "Trace Reporters #", "summary": "**Trace Reporters**\n> This documentation is for an unreleased version of Apache Flink. We recommend you use the latest stable version.\n#  Trace Reporters #\nFlink allows reporting traces to external systems. For more information about Flink’…", "type": "docs-page", "subproject": "flink-core", "version": "master", "lang": "zh", "tags": ["deployment", "flink", "flink-docs-master", "trace_reporters"], "code_langs": [], "last_modified": "2026-07-07", "path_depth": 2}