{"url": "https://nightlies.apache.org/flink/flink-ml-docs-release-2.3/docs/operators/feature/onehotencoder", "title": "", "summary": "**OneHotEncoder**\n##  OneHotEncoder #\nOneHotEncoder maps a categorical feature, represented as a label index, to a binary vector with at most a single one-value indicating the presence of a specific feature value from among the set of all f…", "type": "page", "subproject": "flink-ml", "version": "main", "lang": "en", "tags": ["datastream-api", "feature", "flink", "flink-ml-docs-release-2.3", "onehotencoder", "operators"], "code_langs": [], "last_modified": "2026-07-07", "path_depth": 1}