{"url": "https://nightlies.apache.org/flink/flink-ml-docs-master/docs/operators/feature/kbinsdiscretizer", "title": "", "summary": "**KBinsDiscretizer**\n> This documentation is for an unreleased version of Apache Flink Machine Learning Library. We recommend you use the latest stable version.\n##  KBinsDiscretizer #\nKBinsDiscretizer is an algorithm that implements discret…", "type": "page", "subproject": "flink-ml", "version": "master", "lang": "en", "tags": ["datastream-api", "feature", "flink", "flink-ml-docs-master", "kbinsdiscretizer", "ml", "operators"], "code_langs": [], "last_modified": "2026-07-07", "path_depth": 2}