{"url": "https://nightlies.apache.org/flink/flink-docs-release-1.14/docs/dev/table/overview", "title": "Table API & SQL #", "summary": "**Overview**\n> This documentation is for an out-of-date version of Apache Flink. We recommend you use the latest stable version.\n#  Table API & SQL #\nApache Flink features two relational APIs - the Table API and SQL - for unified stream and…", "type": "docs-page", "subproject": "flink-core", "version": "main", "lang": "en", "tags": ["datastream-api", "dev", "flink", "flink-docs-release-1.14", "overview", "sql", "table", "table-api"], "code_langs": [], "last_modified": "2026-07-07", "path_depth": 2}