{"url": "https://nightlies.apache.org/flink/flink-docs-release-1.16/docs/dev/table/functions/systemfunctions", "title": "System (Built-in) Functions #", "summary": "**System (Built-in) Functions**\n> This documentation is for an out-of-date version of Apache Flink. We recommend you use the latest stable version.\n#  System (Built-in) Functions #\nFlink Table API & SQL provides users with a set of built-in…", "type": "docs-page", "subproject": "flink-core", "version": "main", "lang": "en", "tags": ["dev", "flink", "flink-docs-release-1.16", "functions", "sql", "systemfunctions", "table", "table-api", "watermark", "window"], "code_langs": [], "last_modified": "2026-07-07", "path_depth": 2}