{"url": "https://nightlies.apache.org/flink/flink-docs-release-1.1", "title": "Overview", "summary": "This documentation is for an out-of-date version of Apache Flink. We recommend you use the latest stable version.\n**Important** : Maven artifacts which depend on Scala are now suffixed with the Scala major version, e.g. \"2.10\" or \"2.11\". Pl…", "type": "page", "subproject": "flink-core", "version": "main", "lang": "en", "tags": ["datastream-api", "flink", "flink-docs-release-1.1"], "code_langs": [], "last_modified": "2026-07-06", "path_depth": 1}