{"url": "https://flink.apache.org/zh/how-to-contribute/reviewing-prs", "title": "如何审核 Pull Request #", "summary": "#  如何审核 Pull Request #\n本指南适用于希望帮助审核代码的所有提交者和贡献者。感谢你的努力 - 良好的审核是开源项目中最重要也是最关键的部分之一。本文旨在协助社区开展代码审核工作，以达到下列目的：\n  * 让贡献者拥有良好的贡献体验。\n  * 将审核过程结构化，以涵盖所有需要检查的重要方面。\n  * 保持 Flink 代码的高质量。\n  * 避免贡献者和审核者花费大量时间完善代码却最终被拒绝提交的情况。\n##  审核清单 #\n每次审核都需要检查以下六个方面。…", "type": "page", "subproject": "flink-website", "version": "main", "lang": "zh", "tags": ["checkpoint", "how-to-contribute", "reviewing-prs"], "code_langs": [], "last_modified": "2026-07-06", "path_depth": 1}