{"url": "https://nightlies.apache.org/flink/flink-docs-stable/docs/dev/datastream/operators/overview", "title": "Operators #", "summary": "**Overview**\n#  Operators #\nOperators transform one or more DataStreams into a new DataStream. Programs can combine multiple transformations into sophisticated dataflow topologies.\nThis section gives a description of the basic transformatio…", "type": "docs-page", "subproject": "flink-core", "version": "stable", "lang": "en", "tags": ["datastream", "datastream-api", "dev", "flink", "operators", "overview", "sql", "window"], "code_langs": [], "last_modified": "2026-07-07", "path_depth": 2}