{"url": "https://nightlies.apache.org/flink/flink-docs-release-1.13/docs/ops/state/savepoints", "title": "Savepoints #", "summary": "**Savepoints**\n> This documentation is for an out-of-date version of Apache Flink. We recommend you use the latest stable version.\n#  Savepoints #\n##  What is a Savepoint? How is a Savepoint different from a Checkpoint? #\nA Savepoint is a c…", "type": "docs-page", "subproject": "flink-core", "version": "main", "lang": "en", "tags": ["checkpoint", "datastream-api", "flink", "flink-docs-release-1.13", "ops", "savepoint", "savepoints", "state", "window"], "code_langs": [], "last_modified": "2026-07-07", "path_depth": 2}