{"url": "https://nightlies.apache.org/flink/flink-kubernetes-operator-docs-release-1.15/docs/operations/compatibility", "title": "Compatibility Guarantees #", "summary": "**Compatibility Guarantees**\n#  Compatibility Guarantees #\nIt is very important for users to clearly understand the compatibility guarantees the operator provides when upgrading to new versions.\n##  Custom Resource backward compatibility #…", "type": "page", "subproject": "flink-k8s-operator", "version": "main", "lang": "en", "tags": ["compatibility", "flink", "flink-kubernetes-operator-docs-release-1.15", "k8s", "operations"], "code_langs": [], "last_modified": "2026-07-07", "path_depth": 1}